README.rst
setup.cfg
setup.py
wissen/__init__.py
wissen/binfile.py
wissen/colsetup.py
wissen/docqueue.py
wissen/filesystem.py
wissen/language.py
wissen/memory.py
wissen.egg-info/PKG-INFO
wissen.egg-info/SOURCES.txt
wissen.egg-info/dependency_links.txt
wissen.egg-info/top_level.txt
wissen/extension/wissen/core.c
wissen/extension/wissen/mod_analyzer.c
wissen/extension/wissen/mod_binfile.c
wissen/extension/wissen/mod_bits.c
wissen/extension/wissen/mod_calculator.c
wissen/extension/wissen/mod_classifier.c
wissen/extension/wissen/mod_compute.c
wissen/extension/wissen/mod_dbint.c
wissen/extension/wissen/mod_document.c
wissen/extension/wissen/mod_int.c
wissen/extension/wissen/mod_memorypool.c
wissen/extension/wissen/mod_mergeinfo.c
wissen/extension/wissen/mod_posting.c
wissen/extension/wissen/mod_selector.c
wissen/extension/wissen/mod_sgmlparser.c
wissen/extension/wissen/mod_sortmap.c
wissen/extension/wissen/mod_terminfo.c
wissen/extension/wissen/mod_termtable.c
wissen/extension/wissen/mod_util.c
wissen/extension/wissen/analyzer/analyzer.c
wissen/extension/wissen/analyzer/endword.c
wissen/extension/wissen/analyzer/formalizer.c
wissen/extension/wissen/analyzer/removeaccents.c
wissen/extension/wissen/analyzer/stem.c
wissen/extension/wissen/analyzer/stem_ar.c
wissen/extension/wissen/analyzer/stem_de.c
wissen/extension/wissen/analyzer/stem_es.c
wissen/extension/wissen/analyzer/stem_fi.c
wissen/extension/wissen/analyzer/stem_fr.c
wissen/extension/wissen/analyzer/stem_hu.c
wissen/extension/wissen/analyzer/stem_it.c
wissen/extension/wissen/analyzer/stem_pt.c
wissen/extension/wissen/analyzer/stem_sv.c
wissen/extension/wissen/analyzer/stopword.c
wissen/extension/wissen/index/bfile.c
wissen/extension/wissen/index/compfunc.c
wissen/extension/wissen/index/generichash.c
wissen/extension/wissen/index/heapsort.c
wissen/extension/wissen/index/ibucket.c
wissen/extension/wissen/index/mempool.c
wissen/extension/wissen/index/osutil.c
wissen/extension/wissen/index/search.c
wissen/extension/wissen/index/sort.c
wissen/extension/wissen/index/termhashtable.c
wissen/extension/wissen/index/util.c
