Metadata-Version: 1.1
Name: wissen
Version: 0.12.14.32
Summary: Wissen Full-Text Search & Classification Engine
Home-page: https://gitlab.com/hansroh/wissen
Author: Hans Roh
Author-email: hansroh@gmail.com
License: GPLv3
Download-URL: https://pypi.python.org/pypi/wissen
Platform: posix
Platform: nt
Classifier: License :: OSI Approved :: GNU General Public License v3 (GPLv3)
Classifier: Development Status :: 3 - Alpha
Classifier: Environment :: Console
Classifier: Topic :: Software Development :: Libraries :: Python Modules
Classifier: Intended Audience :: Developers
Classifier: Intended Audience :: Science/Research
Classifier: Programming Language :: Python
Classifier: Programming Language :: Python :: 3
Classifier: Topic :: Text Processing :: Indexing
